beta_iaa_score/__init__.py
beta_iaa_score/core.py
beta_iaa_score-0.1.dist-info/METADATA
beta_iaa_score-0.1.dist-info/WHEEL
beta_iaa_score-0.1.dist-info/top_level.txt
beta_iaa_score-0.1.dist-info/RECORD
