Metadata-Version: 2.1
Name: beta-iaa-score
Version: 0.1
Summary: A Python library that computes Beta IAA score.
Home-page: UNKNOWN
Author: Alexandra Ciobotaru
Author-email: alexandraciobotaru888@gmail.com
License: UNKNOWN
Platform: UNKNOWN
Classifier: Programming Language :: Python :: 3
Classifier: License :: OSI Approved :: MIT License
Classifier: Operating System :: OS Independent
Requires-Python: >=3.6
